human_tar/__init__.py
human_tar/main.py
human_tar-0.1.0.dist-info/licenses/LICENSE
human_tar-0.1.0.dist-info/METADATA
human_tar-0.1.0.dist-info/WHEEL
human_tar-0.1.0.dist-info/entry_points.txt
human_tar-0.1.0.dist-info/top_level.txt
human_tar-0.1.0.dist-info/RECORD
