Metadata-Version: 2.4
Name: human-tar
Version: 0.1.0
Summary: A human-readable tar format for text files, based on grep . -r output
Author-email: "@readwithai" <talwrii@gmail.com>
License: MIT License
Project-URL: Homepage, https://github.com/talwrii/human-tar
Project-URL: Repository, https://github.com/talwrii/human-tar
Project-URL: Issues, https://github.com/talwrii/human-tar/issues
Keywords: grep,tar,file-unpacking,ai-tools
Requires-Python: >=3.6
License-File: LICENSE
Dynamic: license-file
